octane_sdk_wrapper/__about__.py
octane_sdk_wrapper/__init__.py
octane_sdk_wrapper/helpers/__init__.py
octane_sdk_wrapper/helpers/clr2py.py
octane_sdk_wrapper/lib/Impinj.OctaneSdk.dll
octane_sdk_wrapper/lib/LLRP.Impinj.dll
octane_sdk_wrapper/lib/LLRP.dll
octane_sdk_wrapper/lib/Renci.SshNet.dll
octane_sdk_wrapper-1.3.0.dist-info/METADATA
octane_sdk_wrapper-1.3.0.dist-info/WHEEL
octane_sdk_wrapper-1.3.0.dist-info/licenses/LICENSE.txt
octane_sdk_wrapper-1.3.0.dist-info/RECORD
