Metadata-Version: 2.3
Name: octane-sdk-wrapper
Version: 1.3.0
Summary: Python driver for Impinj UHF RFID readers wrapping octane SDK
Project-URL: Documentation, https://github.com/kliskatek/driver-rain-py-octane#readme
Project-URL: Issues, https://github.com/kliskatek/driver-rain-py-octane/issues
Project-URL: Source, https://github.com/kliskatek/driver-rain-py-octane
Author-email: Ibon Zalbide <ibon.zalbide@kliskatek.com>, Aritz Alonso <aritz.alonso@kliskatek.com>
License-Expression: MIT
License-File: LICENSE.txt
Classifier: Development Status :: 4 - Beta
Classifier: Programming Language :: Python
Classifier: Programming Language :: Python :: 3.8
Classifier: Programming Language :: Python :: 3.9
Classifier: Programming Language :: Python :: 3.10
Classifier: Programming Language :: Python :: 3.11
Classifier: Programming Language :: Python :: 3.12
Classifier: Programming Language :: Python :: Implementation :: CPython
Classifier: Programming Language :: Python :: Implementation :: PyPy
Requires-Python: >=3.8
Requires-Dist: dataclasses-json
Requires-Dist: pythonnet
Provides-Extra: dev
Requires-Dist: pytest; extra == 'dev'
